sportstats_sgg/__init__.py
sportstats_sgg/calculos.py
sportstats_sgg-0.1.1.dist-info/METADATA
sportstats_sgg-0.1.1.dist-info/WHEEL
sportstats_sgg-0.1.1.dist-info/top_level.txt
sportstats_sgg-0.1.1.dist-info/RECORD
