Metadata-Version: 2.1
Name: sportstats_sgg
Version: 0.1.1
Summary: Un paquete de ejemplo para análisis deportivo.
Author: Sergio Glez
Author-email: sergiogg97@gmail.com
Classifier: Programming Language :: Python :: 3
Classifier: License :: OSI Approved :: MIT License
Classifier: Operating System :: OS Independent
Requires-Python: >=3.6
